no_thanks/__init__.py
no_thanks/__main__.py
no_thanks/__version__.py
no_thanks/core.py
no_thanks/elo.py
no_thanks/players.py
no_thanks/utils.py
no_thanks/algorithms/__init__.py
no_thanks/algorithms/genetic.py
no_thanks-0.2.2.dist-info/LICENSE
no_thanks-0.2.2.dist-info/METADATA
no_thanks-0.2.2.dist-info/WHEEL
no_thanks-0.2.2.dist-info/entry_points.txt
no_thanks-0.2.2.dist-info/top_level.txt
no_thanks-0.2.2.dist-info/RECORD
