Metadata-Version: 2.1
Name: no-thanks
Version: 0.2.2
Summary: An implementation of Thorsten Gimmler's card game No Thanks!
Home-page: https://gitlab.com/mshepherd/no-thanks
Author: Markus Shepherd
Author-email: no-thanks@recommend.games
License: MIT
Project-URL: Documentation, https://gitlab.com/mshepherd/no-thanks/blob/master/README.md
Project-URL: Source, https://gitlab.com/mshepherd/no-thanks
Project-URL: Tracker, https://gitlab.com/mshepherd/no-thanks/issues
Keywords: no thanks,geschenkt ist noch zu teuer,schöne scheiße,oh shit,game
Classifier: License :: OSI Approved :: MIT License
Classifier: Programming Language :: Python
Classifier: Programming Language :: Python :: 3.6
Classifier: Programming Language :: Python :: 3.7
Classifier: Programming Language :: Python :: 3.8
Classifier: Topic :: Games/Entertainment :: Board Games
Requires-Python: >=3.6.0
License-File: LICENSE
Requires-Dist: inquirer
Requires-Dist: tqdm
